mnist_separator/.DS_Store
mnist_separator/__init__.py
mnist_separator/src/.DS_Store
mnist_separator/src/calc_similarity.py
mnist_separator/src/calc_similarity_2pnts.py
mnist_separator/src/calc_similarity_3pnts.py
mnist_separator/src/calc_similarity_next.py
mnist_separator/src/cfg.py
mnist_separator/src/clean_all.py
mnist_separator/src/convert_data.py
mnist_separator/src/create_dirs.py
mnist_separator/src/get_angle.py
mnist_separator/src/get_peaks.py
mnist_separator/src/get_similarity.py
mnist_separator/src/get_similarity_group.py
mnist_separator/src/glbl.py
mnist_separator/src/go.py
mnist_separator/src/init.py
mnist_separator/src/load_data.py
mnist_separator/src/load_samples.py
mnist_separator/src/magnitude.py
mnist_separator/src/save_result.py
mnist_separator/src/shell_sort.py
mnist_separator/src/sort_peaks.py
mnist_separator/src/timer.py
mnist_separator/src/to_canonical.py
mnist_separator/src/utils_directory.py
mnist_separator/src/utils_list.py
mnist_separator/src/utils_list_of_peaks.py
mnist_separator/src/utils_table.py
mnist_separator-1.0.5.dist-info/METADATA
mnist_separator-1.0.5.dist-info/WHEEL
mnist_separator-1.0.5.dist-info/RECORD
